{"annualChildren":[{"children":[{"lastName":"Mihalache","firstName":"Radu","niceScoreHistory":[10.0],"city":"Cluj-Napoca","giftsPreferences":["Clothes","Board Games"],"assignedBudget":271.8181818181818,"id":0,"receivedGifts":[{"price":45.0,"category":"Clothes","productName":"Dress"},{"price":10.0,"category":"Board Games","productName":"Uno"}],"age":14,"averageScore":10.0},{"lastName":"Stoica","firstName":"Tudor","niceScoreHistory":[4.0],"city":"Brasov","giftsPreferences":["Sweets","Clothes","Board Games","Toys"],"assignedBudget":108.72727272727273,"id":1,"receivedGifts":[{"price":10.0,"category":"Sweets","productName":"Gummy Bears"},{"price":45.0,"category":"Clothes","productName":"Dress"},{"price":10.0,"category":"Board Games","productName":"Uno"},{"price":5.0,"category":"Toys","productName":"Teddy Bear"}],"age":14,"averageScore":4.0},{"lastName":"Mihalache","firstName":"Tudor","niceScoreHistory":[8.0],"city":"Constanta","giftsPreferences":["Technology","Board Games"],"assignedBudget":271.8181818181818,"id":2,"receivedGifts":[{"price":100.0,"category":"Technology","productName":"Headphones"},{"price":10.0,"category":"Board Games","productName":"Uno"}],"age":4,"averageScore":10.0},{"lastName":"Cantemir","firstName":"Alexandra","niceScoreHistory":[5.0],"city":"Craiova","giftsPreferences":["Board Games","Sweets"],"assignedBudget":271.8181818181818,"id":3,"receivedGifts":[{"price":10.0,"category":"Board Games","productName":"Uno"},{"price":10.0,"category":"Sweets","productName":"Gummy Bears"}],"age":4,"averageScore":10.0},{"lastName":"Pop","firstName":"Tudor","niceScoreHistory":[5.0],"city":"Brasov","giftsPreferences":["Toys","Sweets"],"assignedBudget":135.9090909090909,"id":5,"receivedGifts":[{"price":5.0,"category":"Toys","productName":"Teddy Bear"},{"price":10.0,"category":"Sweets","productName":"Gummy Bears"}],"age":17,"averageScore":5.0},{"lastName":"Popa","firstName":"Diana","niceScoreHistory":[4.0],"city":"Cluj-Napoca","giftsPreferences":["Board Games","Toys"],"assignedBudget":271.8181818181818,"id":6,"receivedGifts":[{"price":10.0,"category":"Board Games","productName":"Uno"},{"price":5.0,"category":"Toys","productName":"Teddy Bear"}],"age":2,"averageScore":10.0},{"lastName":"Popescu","firstName":"Radu","niceScoreHistory":[5.0],"city":"Braila","giftsPreferences":["Technology","Clothes","Sweets"],"assignedBudget":135.9090909090909,"id":7,"receivedGifts":[{"price":100.0,"category":"Technology","productName":"Headphones"},{"price":10.0,"category":"Sweets","productName":"Gummy Bears"}],"age":14,"averageScore":5.0},{"lastName":"Mihalache","firstName":"Alexandra","niceScoreHistory":[5.0],"city":"Timisoara","giftsPreferences":["Technology","Sweets"],"assignedBudget":271.8181818181818,"id":8,"receivedGifts":[{"price":100.0,"category":"Technology","productName":"Headphones"},{"price":10.0,"category":"Sweets","productName":"Gummy Bears"}],"age":3,"averageScore":10.0},{"lastName":"Stoica","firstName":"Matei","niceScoreHistory":[2.0],"city":"Timisoara","giftsPreferences":["Technology","Clothes","Toys","Sweets"],"assignedBudget":54.36363636363637,"id":9,"receivedGifts":[{"price":45.0,"category":"Clothes","productName":"Dress"},{"price":5.0,"category":"Toys","productName":"Teddy Bear"}],"age":14,"averageScore":2.0}]},{"children":[{"lastName":"Mihalache","firstName":"Radu","niceScoreHistory":[10.0],"city":"Cluj-Napoca","giftsPreferences":["Clothes","Board Games"],"assignedBudget":260.0,"id":0,"receivedGifts":[{"price":45.0,"category":"Clothes","productName":"Dress"},{"price":10.0,"category":"Board Games","productName":"Uno"}],"age":15,"averageScore":10.0},{"lastName":"Stoica","firstName":"Tudor","niceScoreHistory":[4.0],"city":"Brasov","giftsPreferences":["Sweets","Clothes","Board Games","Toys"],"assignedBudget":104.0,"id":1,"receivedGifts":[{"price":10.0,"category":"Sweets","productName":"Gummy Bears"},{"price":45.0,"category":"Clothes","productName":"Dress"},{"price":10.0,"category":"Board Games","productName":"Uno"},{"price":5.0,"category":"Toys","productName":"Teddy Bear"}],"age":15,"averageScore":4.0},{"lastName":"Mihalache","firstName":"Tudor","niceScoreHistory":[8.0],"city":"Constanta","giftsPreferences":["Technology","Board Games"],"assignedBudget":208.0,"id":2,"receivedGifts":[{"price":100.0,"category":"Technology","productName":"Headphones"},{"price":10.0,"category":"Board Games","productName":"Uno"}],"age":5,"averageScore":8.0},{"lastName":"Cantemir","firstName":"Alexandra","niceScoreHistory":[5.0],"city":"Craiova","giftsPreferences":["Board Games","Sweets"],"assignedBudget":130.0,"id":3,"receivedGifts":[{"price":10.0,"category":"Board Games","productName":"Uno"},{"price":10.0,"category":"Sweets","productName":"Gummy Bears"}],"age":5,"averageScore":5.0},{"lastName":"Pop","firstName":"Tudor","niceScoreHistory":[5.0],"city":"Brasov","giftsPreferences":["Toys","Sweets"],"assignedBudget":130.0,"id":5,"receivedGifts":[{"price":5.0,"category":"Toys","productName":"Teddy Bear"},{"price":10.0,"category":"Sweets","productName":"Gummy Bears"}],"age":18,"averageScore":5.0},{"lastName":"Popa","firstName":"Diana","niceScoreHistory":[4.0],"city":"Cluj-Napoca","giftsPreferences":["Board Games","Toys"],"assignedBudget":260.0,"id":6,"receivedGifts":[{"price":10.0,"category":"Board Games","productName":"Uno"},{"price":5.0,"category":"Toys","productName":"Teddy Bear"}],"age":3,"averageScore":10.0},{"lastName":"Popescu","firstName":"Radu","niceScoreHistory":[5.0],"city":"Braila","giftsPreferences":["Technology","Clothes","Sweets"],"assignedBudget":130.0,"id":7,"receivedGifts":[{"price":100.0,"category":"Technology","productName":"Headphones"},{"price":10.0,"category":"Sweets","productName":"Gummy Bears"}],"age":15,"averageScore":5.0},{"lastName":"Mihalache","firstName":"Alexandra","niceScoreHistory":[5.0],"city":"Timisoara","giftsPreferences":["Technology","Sweets"],"assignedBudget":260.0,"id":8,"receivedGifts":[{"price":100.0,"category":"Technology","productName":"Headphones"},{"price":10.0,"category":"Sweets","productName":"Gummy Bears"}],"age":4,"averageScore":10.0},{"lastName":"Stoica","firstName":"Matei","niceScoreHistory":[2.0],"city":"Timisoara","giftsPreferences":["Technology","Clothes","Toys","Sweets"],"assignedBudget":52.0,"id":9,"receivedGifts":[{"price":45.0,"category":"Clothes","productName":"Dress"},{"price":5.0,"category":"Toys","productName":"Teddy Bear"}],"age":15,"averageScore":2.0},{"lastName":"Pop","firstName":"Diana","niceScoreHistory":[10.0],"city":"Iasi","giftsPreferences":["Technology","Board Games","Sweets"],"assignedBudget":260.0,"id":10,"receivedGifts":[{"price":100.0,"category":"Technology","productName":"Headphones"},{"price":10.0,"category":"Board Games","productName":"Uno"},{"price":10.0,"category":"Sweets","productName":"Gummy Bears"}],"age":5,"averageScore":10.0}]},{"children":[{"lastName":"Mihalache","firstName":"Radu","niceScoreHistory":[10.0],"city":"Cluj-Napoca","giftsPreferences":["Clothes","Board Games"],"assignedBudget":306.6666666666667,"id":0,"receivedGifts":[{"price":45.0,"category":"Clothes","productName":"Dress"},{"price":10.0,"category":"Board Games","productName":"Uno"}],"age":16,"averageScore":10.0},{"lastName":"Stoica","firstName":"Tudor","niceScoreHistory":[4.0],"city":"Brasov","giftsPreferences":["Sweets","Clothes","Board Games","Toys"],"assignedBudget":122.66666666666667,"id":1,"receivedGifts":[{"price":10.0,"category":"Sweets","productName":"Gummy Bears"},{"price":45.0,"category":"Clothes","productName":"Dress"},{"price":10.0,"category":"Board Games","productName":"Uno"},{"price":5.0,"category":"Toys","productName":"Teddy Bear"}],"age":16,"averageScore":4.0},{"lastName":"Mihalache","firstName":"Tudor","niceScoreHistory":[8.0,7.0],"city":"Constanta","giftsPreferences":["Technology","Sweets","Toys","Board Games"],"assignedBudget":230.0,"id":2,"receivedGifts":[{"price":100.0,"category":"Technology","productName":"Headphones"},{"price":10.0,"category":"Sweets","productName":"Gummy Bears"},{"price":5.0,"category":"Toys","productName":"Teddy Bear"},{"price":10.0,"category":"Board Games","productName":"Uno"}],"age":6,"averageScore":7.5},{"lastName":"Cantemir","firstName":"Alexandra","niceScoreHistory":[5.0],"city":"Craiova","giftsPreferences":["Board Games","Sweets"],"assignedBudget":153.33333333333334,"id":3,"receivedGifts":[{"price":10.0,"category":"Board Games","productName":"Uno"},{"price":10.0,"category":"Sweets","productName":"Gummy Bears"}],"age":6,"averageScore":5.0},{"lastName":"Popa","firstName":"Diana","niceScoreHistory":[4.0],"city":"Cluj-Napoca","giftsPreferences":["Board Games","Toys"],"assignedBudget":306.6666666666667,"id":6,"receivedGifts":[{"price":10.0,"category":"Board Games","productName":"Uno"},{"price":5.0,"category":"Toys","productName":"Teddy Bear"}],"age":4,"averageScore":10.0},{"lastName":"Popescu","firstName":"Radu","niceScoreHistory":[5.0],"city":"Braila","giftsPreferences":["Technology","Clothes","Sweets"],"assignedBudget":153.33333333333334,"id":7,"receivedGifts":[{"price":100.0,"category":"Technology","productName":"Headphones"},{"price":45.0,"category":"Clothes","productName":"Dress"}],"age":16,"averageScore":5.0},{"lastName":"Mihalache","firstName":"Alexandra","niceScoreHistory":[5.0],"city":"Timisoara","giftsPreferences":["Technology","Sweets"],"assignedBudget":153.33333333333334,"id":8,"receivedGifts":[{"price":100.0,"category":"Technology","productName":"Headphones"},{"price":10.0,"category":"Sweets","productName":"Gummy Bears"}],"age":5,"averageScore":5.0},{"lastName":"Stoica","firstName":"Matei","niceScoreHistory":[2.0],"city":"Timisoara","giftsPreferences":["Technology","Clothes","Toys","Sweets"],"assignedBudget":61.333333333333336,"id":9,"receivedGifts":[{"price":45.0,"category":"Clothes","productName":"Dress"},{"price":5.0,"category":"Toys","productName":"Teddy Bear"},{"price":10.0,"category":"Sweets","productName":"Gummy Bears"}],"age":16,"averageScore":2.0},{"lastName":"Pop","firstName":"Diana","niceScoreHistory":[10.0],"city":"Iasi","giftsPreferences":["Technology","Board Games","Sweets"],"assignedBudget":306.6666666666667,"id":10,"receivedGifts":[{"price":100.0,"category":"Technology","productName":"Headphones"},{"price":10.0,"category":"Board Games","productName":"Uno"},{"price":10.0,"category":"Sweets","productName":"Gummy Bears"}],"age":6,"averageScore":10.0}]},{"children":[{"lastName":"Mihalache","firstName":"Radu","niceScoreHistory":[10.0],"city":"Cluj-Napoca","giftsPreferences":["Clothes","Board Games"],"assignedBudget":91.85185185185185,"id":0,"receivedGifts":[{"price":45.0,"category":"Clothes","productName":"Dress"},{"price":10.0,"category":"Board Games","productName":"Uno"}],"age":17,"averageScore":10.0},{"lastName":"Stoica","firstName":"Tudor","niceScoreHistory":[4.0],"city":"Brasov","giftsPreferences":["Sweets","Clothes","Board Games","Toys"],"assignedBudget":36.74074074074074,"id":1,"receivedGifts":[{"price":10.0,"category":"Sweets","productName":"Gummy Bears"},{"price":10.0,"category":"Board Games","productName":"Uno"},{"price":5.0,"category":"Toys","productName":"Teddy Bear"}],"age":17,"averageScore":4.0},{"lastName":"Mihalache","firstName":"Tudor","niceScoreHistory":[8.0,7.0],"city":"Constanta","giftsPreferences":["Technology","Sweets","Toys","Board Games"],"assignedBudget":68.88888888888889,"id":2,"receivedGifts":[{"price":10.0,"category":"Sweets","productName":"Gummy Bears"},{"price":5.0,"category":"Toys","productName":"Teddy Bear"},{"price":10.0,"category":"Board Games","productName":"Uno"}],"age":7,"averageScore":7.5},{"lastName":"Cantemir","firstName":"Alexandra","niceScoreHistory":[5.0],"city":"Craiova","giftsPreferences":["Board Games","Sweets"],"assignedBudget":45.925925925925924,"id":3,"receivedGifts":[{"price":10.0,"category":"Board Games","productName":"Uno"},{"price":10.0,"category":"Sweets","productName":"Gummy Bears"}],"age":7,"averageScore":5.0},{"lastName":"Popa","firstName":"Diana","niceScoreHistory":[4.0],"city":"Cluj-Napoca","giftsPreferences":["Board Games","Toys"],"assignedBudget":36.74074074074074,"id":6,"receivedGifts":[{"price":10.0,"category":"Board Games","productName":"Uno"},{"price":5.0,"category":"Toys","productName":"Teddy Bear"}],"age":5,"averageScore":4.0},{"lastName":"Popescu","firstName":"Radu","niceScoreHistory":[5.0],"city":"Braila","giftsPreferences":["Technology","Clothes","Sweets"],"assignedBudget":45.925925925925924,"id":7,"receivedGifts":[{"price":45.0,"category":"Clothes","productName":"Dress"}],"age":17,"averageScore":5.0},{"lastName":"Mihalache","firstName":"Alexandra","niceScoreHistory":[5.0],"city":"Timisoara","giftsPreferences":["Technology","Sweets"],"assignedBudget":45.925925925925924,"id":8,"receivedGifts":[{"price":10.0,"category":"Sweets","productName":"Gummy Bears"}],"age":6,"averageScore":5.0},{"lastName":"Stoica","firstName":"Matei","niceScoreHistory":[2.0],"city":"Timisoara","giftsPreferences":["Technology","Clothes","Toys","Sweets"],"assignedBudget":18.37037037037037,"id":9,"receivedGifts":[{"price":5.0,"category":"Toys","productName":"Teddy Bear"},{"price":10.0,"category":"Sweets","productName":"Gummy Bears"}],"age":17,"averageScore":2.0},{"lastName":"Pop","firstName":"Diana","niceScoreHistory":[10.0],"city":"Iasi","giftsPreferences":["Technology","Board Games","Sweets"],"assignedBudget":91.85185185185185,"id":10,"receivedGifts":[{"price":10.0,"category":"Board Games","productName":"Uno"},{"price":10.0,"category":"Sweets","productName":"Gummy Bears"}],"age":7,"averageScore":10.0},{"lastName":"Stoica","firstName":"Mihai","niceScoreHistory":[9.0],"city":"Cluj-Napoca","giftsPreferences":["Toys","Sweets"],"assignedBudget":82.66666666666667,"id":12,"receivedGifts":[{"price":5.0,"category":"Toys","productName":"Teddy Bear"},{"price":10.0,"category":"Sweets","productName":"Gummy Bears"}],"age":12,"averageScore":9.0},{"lastName":"Popescu","firstName":"Diana","niceScoreHistory":[6.0],"city":"Bucuresti","giftsPreferences":["Sweets"],"assignedBudget":55.111111111111114,"id":13,"receivedGifts":[{"price":10.0,"category":"Sweets","productName":"Gummy Bears"}],"age":10,"averageScore":6.0}]},{"children":[{"lastName":"Mihalache","firstName":"Radu","niceScoreHistory":[10.0],"city":"Cluj-Napoca","giftsPreferences":["Clothes","Board Games"],"assignedBudget":61.62962962962963,"id":0,"receivedGifts":[{"price":45.0,"category":"Clothes","productName":"Dress"},{"price":10.0,"category":"Board Games","productName":"Uno"}],"age":18,"averageScore":10.0},{"lastName":"Stoica","firstName":"Tudor","niceScoreHistory":[4.0],"city":"Brasov","giftsPreferences":["Sweets","Clothes","Board Games","Toys"],"assignedBudget":24.651851851851852,"id":1,"receivedGifts":[{"price":10.0,"category":"Sweets","productName":"Gummy Bears"},{"price":10.0,"category":"Board Games","productName":"Uno"}],"age":18,"averageScore":4.0},{"lastName":"Mihalache","firstName":"Tudor","niceScoreHistory":[8.0,7.0],"city":"Constanta","giftsPreferences":["Technology","Sweets","Toys","Board Games"],"assignedBudget":46.22222222222222,"id":2,"receivedGifts":[{"price":10.0,"category":"Sweets","productName":"Gummy Bears"},{"price":5.0,"category":"Toys","productName":"Teddy Bear"},{"price":10.0,"category":"Board Games","productName":"Uno"}],"age":8,"averageScore":7.5},{"lastName":"Cantemir","firstName":"Alexandra","niceScoreHistory":[5.0],"city":"Craiova","giftsPreferences":["Board Games","Sweets"],"assignedBudget":30.814814814814817,"id":3,"receivedGifts":[{"price":10.0,"category":"Board Games","productName":"Uno"},{"price":10.0,"category":"Sweets","productName":"Gummy Bears"}],"age":8,"averageScore":5.0},{"lastName":"Popa","firstName":"Diana","niceScoreHistory":[4.0],"city":"Cluj-Napoca","giftsPreferences":["Board Games","Toys"],"assignedBudget":24.651851851851852,"id":6,"receivedGifts":[{"price":10.0,"category":"Board Games","productName":"Uno"},{"price":5.0,"category":"Toys","productName":"Teddy Bear"}],"age":6,"averageScore":4.0},{"lastName":"Popescu","firstName":"Radu","niceScoreHistory":[5.0],"city":"Braila","giftsPreferences":["Technology","Clothes","Sweets"],"assignedBudget":30.814814814814817,"id":7,"receivedGifts":[{"price":10.0,"category":"Sweets","productName":"Gummy Bears"}],"age":18,"averageScore":5.0},{"lastName":"Mihalache","firstName":"Alexandra","niceScoreHistory":[5.0],"city":"Timisoara","giftsPreferences":["Technology","Sweets"],"assignedBudget":30.814814814814817,"id":8,"receivedGifts":[{"price":10.0,"category":"Sweets","productName":"Gummy Bears"}],"age":7,"averageScore":5.0},{"lastName":"Stoica","firstName":"Matei","niceScoreHistory":[2.0],"city":"Timisoara","giftsPreferences":["Technology","Clothes","Toys","Sweets"],"assignedBudget":12.325925925925926,"id":9,"receivedGifts":[{"price":5.0,"category":"Toys","productName":"Teddy Bear"}],"age":18,"averageScore":2.0},{"lastName":"Pop","firstName":"Diana","niceScoreHistory":[10.0],"city":"Iasi","giftsPreferences":["Technology","Board Games","Sweets"],"assignedBudget":61.62962962962963,"id":10,"receivedGifts":[{"price":10.0,"category":"Board Games","productName":"Uno"},{"price":10.0,"category":"Sweets","productName":"Gummy Bears"}],"age":8,"averageScore":10.0},{"lastName":"Stoica","firstName":"Mihai","niceScoreHistory":[9.0],"city":"Cluj-Napoca","giftsPreferences":["Toys","Sweets"],"assignedBudget":55.46666666666667,"id":12,"receivedGifts":[{"price":5.0,"category":"Toys","productName":"Teddy Bear"},{"price":10.0,"category":"Sweets","productName":"Gummy Bears"}],"age":13,"averageScore":9.0},{"lastName":"Popescu","firstName":"Diana","niceScoreHistory":[6.0],"city":"Bucuresti","giftsPreferences":["Sweets"],"assignedBudget":36.977777777777774,"id":13,"receivedGifts":[{"price":10.0,"category":"Sweets","productName":"Gummy Bears"}],"age":11,"averageScore":6.0}]},{"children":[{"lastName":"Mihalache","firstName":"Tudor","niceScoreHistory":[8.0,7.0],"city":"Constanta","giftsPreferences":["Technology","Sweets","Toys","Board Games"],"assignedBudget":109.00763358778626,"id":2,"receivedGifts":[{"price":100.0,"category":"Technology","productName":"Headphones"},{"price":5.0,"category":"Toys","productName":"Teddy Bear"}],"age":9,"averageScore":7.5},{"lastName":"Cantemir","firstName":"Alexandra","niceScoreHistory":[5.0],"city":"Craiova","giftsPreferences":["Board Games","Sweets"],"assignedBudget":72.67175572519083,"id":3,"receivedGifts":[{"price":10.0,"category":"Board Games","productName":"Uno"},{"price":10.0,"category":"Sweets","productName":"Gummy Bears"}],"age":9,"averageScore":5.0},{"lastName":"Popa","firstName":"Diana","niceScoreHistory":[4.0],"city":"Cluj-Napoca","giftsPreferences":["Board Games","Toys"],"assignedBudget":58.13740458015267,"id":6,"receivedGifts":[{"price":10.0,"category":"Board Games","productName":"Uno"},{"price":5.0,"category":"Toys","productName":"Teddy Bear"}],"age":7,"averageScore":4.0},{"lastName":"Mihalache","firstName":"Alexandra","niceScoreHistory":[5.0],"city":"Timisoara","giftsPreferences":["Technology","Sweets"],"assignedBudget":72.67175572519083,"id":8,"receivedGifts":[{"price":10.0,"category":"Sweets","productName":"Gummy Bears"}],"age":8,"averageScore":5.0},{"lastName":"Pop","firstName":"Diana","niceScoreHistory":[10.0],"city":"Iasi","giftsPreferences":["Technology","Board Games","Sweets"],"assignedBudget":145.34351145038167,"id":10,"receivedGifts":[{"price":100.0,"category":"Technology","productName":"Headphones"},{"price":10.0,"category":"Board Games","productName":"Uno"},{"price":10.0,"category":"Sweets","productName":"Gummy Bears"}],"age":9,"averageScore":10.0},{"lastName":"Stoica","firstName":"Mihai","niceScoreHistory":[9.0],"city":"Cluj-Napoca","giftsPreferences":["Toys","Sweets"],"assignedBudget":130.8091603053435,"id":12,"receivedGifts":[{"price":5.0,"category":"Toys","productName":"Teddy Bear"},{"price":10.0,"category":"Sweets","productName":"Gummy Bears"}],"age":14,"averageScore":9.0},{"lastName":"Popescu","firstName":"Diana","niceScoreHistory":[6.0],"city":"Bucuresti","giftsPreferences":["Sweets"],"assignedBudget":87.20610687022901,"id":13,"receivedGifts":[{"price":10.0,"category":"Sweets","productName":"Gummy Bears"}],"age":12,"averageScore":6.0},{"lastName":"Cantemir","firstName":"Tudor","niceScoreHistory":[9.0],"city":"Timisoara","giftsPreferences":["Technology","Board Games","Toys"],"assignedBudget":130.8091603053435,"id":14,"receivedGifts":[{"price":100.0,"category":"Technology","productName":"Headphones"},{"price":10.0,"category":"Board Games","productName":"Uno"},{"price":5.0,"category":"Toys","productName":"Teddy Bear"}],"age":14,"averageScore":9.0},{"lastName":"Popa","firstName":"Mihai","niceScoreHistory":[9.0],"city":"Bucuresti","giftsPreferences":["Sweets","Clothes","Toys"],"assignedBudget":145.34351145038167,"id":15,"receivedGifts":[{"price":10.0,"category":"Sweets","productName":"Gummy Bears"},{"price":45.0,"category":"Clothes","productName":"Dress"},{"price":5.0,"category":"Toys","productName":"Teddy Bear"}],"age":1,"averageScore":10.0}]}]}